LICENSE
MANIFEST.in
README.md
setup.cfg
setup.py
bmi_arcgis_restapi.egg-info/PKG-INFO
bmi_arcgis_restapi.egg-info/SOURCES.txt
bmi_arcgis_restapi.egg-info/dependency_links.txt
bmi_arcgis_restapi.egg-info/requires.txt
bmi_arcgis_restapi.egg-info/top_level.txt
restapi/__init__.py
restapi/_strings.py
restapi/arc_restapi.py
restapi/common_types.py
restapi/conversion.py
restapi/enums.py
restapi/exceptions.py
restapi/globals.py
restapi/open_restapi.py
restapi/rest_utils.py
restapi/shapefile.py
restapi/admin/__init__.py
restapi/admin/utils.py
restapi/admin/samples/admin_samples.py
restapi/decorator/__init__.py
restapi/geometry-helper/favicon.ico
restapi/geometry-helper/index.html
restapi/geometry-helper/manifest.json
restapi/geometry-helper/precache-manifest.b62ded22fc8a9700861c815d7e20acbd.js
restapi/geometry-helper/robots.txt
restapi/geometry-helper/service-worker.js
restapi/geometry-helper/css/app.615af0e5.css
restapi/geometry-helper/css/chunk-26ed89da.8fb689c1.css
restapi/geometry-helper/css/chunk-vendors.64d43e69.css
restapi/geometry-helper/img/icons/android-chrome-192x192.png
restapi/geometry-helper/img/icons/android-chrome-512x512.png
restapi/geometry-helper/img/icons/android-chrome-maskable-192x192.png
restapi/geometry-helper/img/icons/android-chrome-maskable-512x512.png
restapi/geometry-helper/img/icons/apple-touch-icon-120x120.png
restapi/geometry-helper/img/icons/apple-touch-icon-152x152.png
restapi/geometry-helper/img/icons/apple-touch-icon-180x180.png
restapi/geometry-helper/img/icons/apple-touch-icon-60x60.png
restapi/geometry-helper/img/icons/apple-touch-icon-76x76.png
restapi/geometry-helper/img/icons/apple-touch-icon.png
restapi/geometry-helper/img/icons/favicon-16x16.png
restapi/geometry-helper/img/icons/favicon-32x32.png
restapi/geometry-helper/img/icons/msapplication-icon-144x144.png
restapi/geometry-helper/img/icons/mstile-150x150.png
restapi/geometry-helper/img/icons/safari-pinned-tab.svg
restapi/geometry-helper/js/app.dbaf9f92.js
restapi/geometry-helper/js/chunk-26ed89da.db4a4cda.js
restapi/geometry-helper/js/chunk-vendors.20697101.js
restapi/projections/__init__.py
restapi/projections/bin/gtf.json
restapi/projections/bin/linearUnits.json
